sdes/__init__.py
sdes/sdes.py
sdes-0.1.3.dist-info/METADATA
sdes-0.1.3.dist-info/WHEEL
sdes-0.1.3.dist-info/top_level.txt
sdes-0.1.3.dist-info/RECORD
