Metadata-Version: 2.1
Name: sdes
Version: 0.1.3
Summary: Simplified Data Encryption Standard (S-DES) Implementation
Author: Mike The Gold Head
Author-email: mrgoldhead21@proton.me
License: MIT
Classifier: Programming Language :: Python :: 3
Classifier: License :: OSI Approved :: MIT License
Classifier: Operating System :: OS Independent
Requires-Python: >=3.6
Requires-Dist: bitarray
